lyberry_qt/__init__.py
lyberry_qt/__main__.py
lyberry_qt/channel_screen.py
lyberry_qt/comment_screen.py
lyberry_qt/connect.py
lyberry_qt/feed_screen.py
lyberry_qt/helpers.py
lyberry_qt/pub_screen.py
lyberry_qt/qt_window.py
lyberry_qt/settings.py
lyberry_qt/designer/account.ui
lyberry_qt/designer/article.ui
lyberry_qt/designer/channel.ui
lyberry_qt/designer/comment.ui
lyberry_qt/designer/comment_screen.ui
lyberry_qt/designer/connecting.ui
lyberry_qt/designer/following.ui
lyberry_qt/designer/main.ui
lyberry_qt/designer/pub.ui
lyberry_qt/designer/pub_thumb.ui
lyberry_qt/designer/settings.ui
lyberry_qt/designer/write_comment.ui
lyberry_qt/images/NotFound.png
lyberry_qt-0.2.4.dist-info/LICENSE.txt
lyberry_qt-0.2.4.dist-info/METADATA
lyberry_qt-0.2.4.dist-info/WHEEL
lyberry_qt-0.2.4.dist-info/entry_points.txt
lyberry_qt-0.2.4.dist-info/top_level.txt
lyberry_qt-0.2.4.dist-info/RECORD
