Metadata-Version: 2.1
Name: lyberry-qt
Version: 0.2.4
Summary: A qt LBRY client using the lyberry api
Home-page: https://git.thebeanbakery.xyz/beans/lyberry_qt
Author: MyBeansAreBaked
Author-email: tristan@tristans.cloud
License: GPLv3+
Platform: UNKNOWN
Classifier: Programming Language :: Python :: 3
Classifier: License :: OSI Approved :: GNU General Public License v3 or later (GPLv3+)
Classifier: Operating System :: OS Independent
Requires-Python: >=3.7
License-File: LICENSE.txt
Requires-Dist: lyberry-api (==0.2.2)
Requires-Dist: pyqt5
Requires-Dist: requests
